setup.py
eyes_on_me/__init__.py
eyes_on_me/backlight.py
eyes_on_me/config.py
eyes_on_me/lights.py
eyes_on_me/strategy.py
eyes_on_me/temperature.py
eyes_on_me/timed_strategy.py
eyes_on_me/webcam_strategy.py
eyes_on_me.egg-info/PKG-INFO
eyes_on_me.egg-info/SOURCES.txt
eyes_on_me.egg-info/dependency_links.txt
eyes_on_me.egg-info/requires.txt
eyes_on_me.egg-info/top_level.txt
eyes_on_me/bin/eyes_on_me