Metadata-Version: 1.0
Name: eyes-on-me
Version: 0.5
Summary: eyes_on_me is simple utility which allows you to control your screen backlight and temperature according to lighting
Home-page: https://bitbucket.org/dehun/eyes_on_me/
Author: Yuriy Netesov
Author-email: yuriy.netesov@gmail.com
License: BSD
Platform: UNKNOWN
